[
  {
    "ip": "8.8.8.8",
    "timestamp": "2025-04-28T21:42:05.917265",
    "result": {
      "success": true,
      "service": "ipinfo",
      "data": {
        "ip": "8.8.8.8",
        "hostname": "dns.google",
        "city": "Mountain View",
        "region": "California",
        "country": "US",
        "loc": "38.0088,-122.1175",
        "org": "AS15169 Google LLC",
        "postal": "94043",
        "timezone": "America/Los_Angeles",
        "readme": "https://ipinfo.io/missingauth",
        "anycast": true
      },
      "timestamp": "2025-04-28T21:42:05.916902"
    }
  },
  {
    "ip": "8.8.8.8",
    "timestamp": "2025-04-28T21:20:48.635404",
    "result": {
      "success": true,
      "service": "ipinfo",
      "data": {
        "ip": "8.8.8.8",
        "hostname": "dns.google",
        "city": "Mountain View",
        "region": "California",
        "country": "US",
        "loc": "38.0088,-122.1175",
        "org": "AS15169 Google LLC",
        "postal": "94043",
        "timezone": "America/Los_Angeles",
        "readme": "https://ipinfo.io/missingauth",
        "anycast": true
      },
      "timestamp": "2025-04-28T21:20:48.635192"
    }
  }
]